CHANGELOG.md
LICENSE
MANIFEST.in
README.md
setup.cfg
setup.py
osmosis_streaming_driver/__init__.py
osmosis_streaming_driver/computing_plugin.py
osmosis_streaming_driver/data_plugin.py
osmosis_streaming_driver.egg-info/PKG-INFO
osmosis_streaming_driver.egg-info/SOURCES.txt
osmosis_streaming_driver.egg-info/dependency_links.txt
osmosis_streaming_driver.egg-info/not-zip-safe
osmosis_streaming_driver.egg-info/requires.txt
osmosis_streaming_driver.egg-info/top_level.txt
osmosis_streaming_driver/proxy_server/__init__.py
osmosis_streaming_driver/proxy_server/run.py
osmosis_streaming_driver/proxy_server/token_store.py
tests/test_data_plugin.py
tests/test_proxy_server.py
tests/test_token_store.py