Metadata-Version: 2.1
Name: osmosis-streaming-driver
Version: 0.0.5
Summary: 💧 Osmosis Streaming Driver Implementation
Home-page: https://github.com/marcojrfurtado/osmosis-streaming-driver
Author: marcojrfurtado
Author-email: 
License: Apache Software License 2.0
Keywords: osmosis-streaming-driver
Platform: UNKNOWN
Classifier: Development Status :: 2 - Pre-Alpha
Classifier: Intended Audience :: Developers
Classifier: License :: OSI Approved :: Apache Software License
Classifier: Natural Language :: English
Classifier: Programming Language :: Python :: 3.6
Classifier: Programming Language :: Python :: 3.7
Provides-Extra: dev
Provides-Extra: docs
Provides-Extra: test
